[
  {
    "slug": "infraimpact-ecomonitor-mki-stuurinstrument",
    "title": "InfraImpact × Eco Monitor – MKI als stuurinstrument voor beleid, aanbesteding en projecten",
    "client": "Eco Monitor × InfraImpact",
    "type": "Samenwerking",
    "tags": ["Samenwerking", "MKI", "LCA", "Sturingsinstrument", "Beleid", "Aanbesteding", "GWW", "Eco Monitor"],
    "summary": "Strategische partnersamenwerking waarin InfraImpact en Eco Monitor de LCA-systematiek inzetten als stuurinstrument, met focus op uitvoering, duiding, kennisdeling en consistente toepassing binnen beleid, aanbestedingen en projecten.",
    "collaboration": "In samenwerking",
    "hero": "/assets/Eco_Monitor_achtergrond.jpg",
    "date": "2026-01",
    "url": "/projecten/infraimpact-ecomonitor-mki-stuurinstrument/"
  },
  {
    "slug": "nmd-gww-perceel-6-h80-h81",
    "title": "NMD – GWW Perceel 6 (H80/H81): actualisatie categorie 3 data & LCA-berekening",
    "client": "Nationale Milieudatabase (NMD)",
    "type": "LCA",
    "tags": ["NMD", "GWW", "Perceel 6", "Categorie 3", "RAW", "H80", "H81", "Excel", "Review-proof"],
    "summary": "Actualisatie van categorie 1/2/3 data en categorie 3 controle (incl. decompositie, biogene CO₂, module D, classificatie), herstructurering/opstellen rapportage conform NMD-template, LCA-berekening verwerking, verwerken review-feedback en invoer van aangepaste data in het NMD-platform.",
    "collaboration": "Zelfstandig",
    "hero": "/assets/NMD_achtergrond.jpg",
    "date": "2025-11",
    "url": "/projecten/nmd-gww-perceel-6/"
  }
]
